dpyp/__init__.py
dpyp/calculate.py
dpyp/clean.py
dpyp/diagnose.py
dpyp/read.py
dpyp/text.py
dpyp/write.py
dpypr/__init__.py
dpypr/calculate.py
dpypr/clean.py
dpypr/diagnose.py
dpypr/read.py
dpypr/write.py
dpyp-1.0.0.dist-info/LICENSE.md
dpyp-1.0.0.dist-info/METADATA
dpyp-1.0.0.dist-info/WHEEL
dpyp-1.0.0.dist-info/top_level.txt
dpyp-1.0.0.dist-info/RECORD
