Metadata-Version: 2.1
Name: dpyp
Version: 1.0.0
Summary: A pandas convenience wrapper for small-scale data pipelines
Home-page: https://github.com/buchananja/dpyp
Author: James Buchanan
Author-email: buchananja.github@pm.me
License: MIT
Keywords: pandas,data,pipeline,cleaning,processing
License-File: LICENSE.md
Requires-Dist: pandas
Requires-Dist: pyarrow
